pypi_query_mcp/__init__.py
pypi_query_mcp/consolidated_tools.py
pypi_query_mcp/server.py
pypi_query_mcp/config/__init__.py
pypi_query_mcp/config/repository.py
pypi_query_mcp/config/settings.py
pypi_query_mcp/core/__init__.py
pypi_query_mcp/core/dependency_parser.py
pypi_query_mcp/core/exceptions.py
pypi_query_mcp/core/github_client.py
pypi_query_mcp/core/pypi_client.py
pypi_query_mcp/core/rate_limit_config.py
pypi_query_mcp/core/rate_limiter.py
pypi_query_mcp/core/search_client.py
pypi_query_mcp/core/stats_client.py
pypi_query_mcp/core/version_utils.py
pypi_query_mcp/data/__init__.py
pypi_query_mcp/data/popular_packages.py
pypi_query_mcp/prompts/__init__.py
pypi_query_mcp/prompts/dependency_management.py
pypi_query_mcp/prompts/environment_analysis.py
pypi_query_mcp/prompts/migration_guidance.py
pypi_query_mcp/prompts/package_analysis.py
pypi_query_mcp/prompts/trending_analysis.py
pypi_query_mcp/reports/README.md
pypi_query_mcp/reports/__init__.py
pypi_query_mcp/reports/html_reporter.py
pypi_query_mcp/reports/report_data.py
pypi_query_mcp/reports/test_integration.py
pypi_query_mcp/security/__init__.py
pypi_query_mcp/security/credentials.py
pypi_query_mcp/security/input_validator.py
pypi_query_mcp/security/validation.py
pypi_query_mcp/tools/__init__.py
pypi_query_mcp/tools/analytics.py
pypi_query_mcp/tools/community.py
pypi_query_mcp/tools/compatibility_check.py
pypi_query_mcp/tools/dependency_resolver.py
pypi_query_mcp/tools/discovery.py
pypi_query_mcp/tools/download_stats.py
pypi_query_mcp/tools/health_scorer.py
pypi_query_mcp/tools/health_tools.py
pypi_query_mcp/tools/license_analyzer.py
pypi_query_mcp/tools/license_tools.py
pypi_query_mcp/tools/metadata.py
pypi_query_mcp/tools/package_downloader.py
pypi_query_mcp/tools/package_query.py
pypi_query_mcp/tools/publishing.py
pypi_query_mcp/tools/requirements_analyzer.py
pypi_query_mcp/tools/requirements_tools.py
pypi_query_mcp/tools/search.py
pypi_query_mcp/tools/workflow.py
mcpypi-2025.9.30.1.dist-info/METADATA
mcpypi-2025.9.30.1.dist-info/WHEEL
mcpypi-2025.9.30.1.dist-info/entry_points.txt
mcpypi-2025.9.30.1.dist-info/licenses/LICENSE
mcpypi-2025.9.30.1.dist-info/RECORD
