Metadata-Version: 2.4
Name: mcpypi
Version: 2025.9.30.1
Summary: 🎤 mcpypi - Your Master of Ceremonies for PyPI! The ultimate PyPI package intelligence platform through Model Context Protocol (MCP)
Project-URL: Homepage, https://github.com/rsp2k/pypi-query-mcp-server
Project-URL: Repository, https://github.com/rsp2k/pypi-query-mcp-server
Project-URL: Documentation, https://github.com/rsp2k/pypi-query-mcp-server
Author-email: Ryan Malloy <ryan@supported.systems>
License-Expression: MIT
License-File: LICENSE
Keywords: analysis,claude,dependency,intelligence,license,mcp,package,pypi,python,security
Classifier: Development Status :: 5 - Production/Stable
Classifier: Framework :: AsyncIO
Classifier: Intended Audience :: Developers
Classifier: License :: OSI Approved :: MIT License
Classifier: Operating System :: OS Independent
Classifier: Programming Language :: Python :: 3
Classifier: Programming Language :: Python :: 3.10
Classifier: Programming Language :: Python :: 3.11
Classifier: Programming Language :: Python :: 3.12
Classifier: Topic :: Security
Classifier: Topic :: Software Development :: Libraries :: Python Modules
Classifier: Topic :: System :: Software Distribution
Classifier: Topic :: System :: Systems Administration
Requires-Python: >=3.10
Requires-Dist: click==8.1.7
Requires-Dist: fastmcp>=2.0.0
Requires-Dist: feedparser>=6.0.0
Requires-Dist: httpx>=0.28.0
Requires-Dist: packaging>=24.0
Requires-Dist: pydantic-settings>=2.0.0
Requires-Dist: pydantic>=2.0.0
Provides-Extra: dev
Requires-Dist: pre-commit>=4.0.0; extra == 'dev'
Requires-Dist: pytest-asyncio>=0.23.0; extra == 'dev'
Requires-Dist: pytest-cov>=6.0.0; extra == 'dev'
Requires-Dist: pytest-mock>=3.12.0; extra == 'dev'
Requires-Dist: pytest>=8.0.0; extra == 'dev'
Requires-Dist: ruff>=0.12.0; extra == 'dev'
